skill_speak/LICENSE
skill_speak/LICENSE.md
skill_speak/README.md
skill_speak/__init__.py
skill_speak/skill.json
skill_speak/version.py
skill_speak/locale/ca-es/speak.intent
skill_speak/locale/cs-cz/speak.intent
skill_speak/locale/da-dk/speak.intent
skill_speak/locale/de-de/speak.intent
skill_speak/locale/el-gr/speak.intent
skill_speak/locale/en-us/speak.intent
skill_speak/locale/es-es/speak.intent
skill_speak/locale/es-lm/speak.intent
skill_speak/locale/eu-eu/speak.intent
skill_speak/locale/fa-ir/speak.intent
skill_speak/locale/fr-fr/speak.intent
skill_speak/locale/ga-ie/speak.intent
skill_speak/locale/gl-es/speak.intent
skill_speak/locale/hu-hu/speak.intent
skill_speak/locale/it-it/speak.intent
skill_speak/locale/kab-dz/speak.intent
skill_speak/locale/nl-nl/speak.intent
skill_speak/locale/pl-pl/speak.intent
skill_speak/locale/pt-br/speak.intent
skill_speak/locale/ro-ro/speak.intent
skill_speak/locale/ru-ru/speak.intent
skill_speak/locale/sv-se/speak.intent
skill_speak/locale/tr-tr/speak.intent
skill_speak/neon_skill_speak.egg-info/PKG-INFO
skill_speak/neon_skill_speak.egg-info/SOURCES.txt
skill_speak/neon_skill_speak.egg-info/dependency_links.txt
skill_speak/neon_skill_speak.egg-info/entry_points.txt
skill_speak/neon_skill_speak.egg-info/requires.txt
skill_speak/neon_skill_speak.egg-info/top_level.txt
neon_skill_speak-2.0.3.dist-info/LICENSE
neon_skill_speak-2.0.3.dist-info/LICENSE.md
neon_skill_speak-2.0.3.dist-info/METADATA
neon_skill_speak-2.0.3.dist-info/WHEEL
neon_skill_speak-2.0.3.dist-info/entry_points.txt
neon_skill_speak-2.0.3.dist-info/top_level.txt
neon_skill_speak-2.0.3.dist-info/RECORD
